quart_rapidoc/__init__.py
quart_rapidoc/htmls.py
quart_rapidoc/rapidoc-min.js
quart_rapidoc/version.py
tests/__init__.py
tests/quart_rapidoc_tests/__init__.py
tests/quart_rapidoc_tests/petstore.json
tests/quart_rapidoc_tests/petstore.yml
tests/quart_rapidoc_tests/test_quart_rapidoc.py
Quart_Rapidoc-0.5.1.dist-info/LICENSE
Quart_Rapidoc-0.5.1.dist-info/METADATA
Quart_Rapidoc-0.5.1.dist-info/WHEEL
Quart_Rapidoc-0.5.1.dist-info/top_level.txt
Quart_Rapidoc-0.5.1.dist-info/RECORD
