Metadata-Version: 2.1
Name: Quart-Rapidoc
Version: 0.5.1
Summary: Rapidoc support for openapi sepc
Home-page: https://github.com/marirs/quart-rapidoc
Author: Sriram G
Author-email: marirs@gmail.com
License: MIT
Platform: UNKNOWN
Classifier: Development Status :: 5 - Production/Stable
Classifier: Environment :: Web Environment
Classifier: Intended Audience :: Developers
Classifier: License :: OSI Approved :: MIT License
Classifier: Operating System :: MacOS :: MacOS X
Classifier: Operating System :: Unix
Classifier: Programming Language :: Python :: 3.7
Classifier: Programming Language :: Python :: 3.8
Classifier: Topic :: Internet :: WWW/HTTP :: Dynamic Content
Classifier: Topic :: Software Development :: Libraries :: Python Modules
Requires-Python: >=3.7
Requires-Dist: Quart (>=0.12.0)
Requires-Dist: PyYAML (>=5.3)
Provides-Extra: all
Requires-Dist: coverage (>=4.5) ; extra == 'all'
Requires-Dist: coveralls (>=1.8) ; extra == 'all'
Requires-Dist: pytest (>=5.2) ; extra == 'all'
Requires-Dist: pytest-cov (>=2.8) ; extra == 'all'
Requires-Dist: pytest-pep8 (>=1.0) ; extra == 'all'
Requires-Dist: pydocstyle (>=4.0) ; extra == 'all'
Provides-Extra: tests
Requires-Dist: coverage (>=4.5) ; extra == 'tests'
Requires-Dist: coveralls (>=1.8) ; extra == 'tests'
Requires-Dist: pytest (>=5.2) ; extra == 'tests'
Requires-Dist: pytest-cov (>=2.8) ; extra == 'tests'
Requires-Dist: pytest-pep8 (>=1.0) ; extra == 'tests'
Requires-Dist: pydocstyle (>=4.0) ; extra == 'tests'
